properjpg/__init__.py
properjpg/cli.py
properjpg/filesmanager.py
properjpg/processing.py
properjpg-0.3.6.dist-info/LICENSE
properjpg-0.3.6.dist-info/METADATA
properjpg-0.3.6.dist-info/WHEEL
properjpg-0.3.6.dist-info/entry_points.txt
properjpg-0.3.6.dist-info/RECORD
