Metadata-Version: 2.1
Name: properjpg
Version: 0.3.6
Summary: CLI tool to convert almost any image to optimized JPEGs.Fast.
Home-page: https://github.com/vitorrloureiro/properjpg
License: MIT
Keywords: image,optimize,jpg,conversor,web,cli
Author: Vitor Loureiro
Author-email: miseravel.cruller-0o@icloud.com
Requires-Python: >=3.10,<4.0
Classifier: Development Status :: 3 - Alpha
Classifier: Intended Audience :: End Users/Desktop
Classifier: License :: OSI Approved :: MIT License
Classifier: Natural Language :: English
Classifier: Operating System :: OS Independent
Classifier: Programming Language :: Python :: 3
Classifier: Programming Language :: Python :: 3.10
Classifier: Programming Language :: Python :: 3.11
Classifier: Programming Language :: Python :: 3.12
Classifier: Topic :: Utilities
Classifier: Typing :: Typed
Requires-Dist: Pillow (>=10.2.0,<11.0.0)
Project-URL: Documentation, https://github.com/vitorrloureiro/properjpg
Project-URL: Repository, https://github.com/vitorrloureiro/properjpg
